Library/ActionGen.py
Library/Container.py
Library/Enums.py
Library/FileAccess.py
Library/GenControllers.py
Library/GenCshape.py
Library/GenEnumCs.py
Library/GenInterface.py
Library/GenRepository.py
Library/ReadXls.py
Library/__init__.py
tests/__init__.py
tests/test_1_readxls.py
tests/test_2_genClass.py
tests/test_3_genControllers.py
tests/test_4_genInterface.py
tests/test_5_genRepository.py
gendotnetclass-0.0.1.dist-info/METADATA
gendotnetclass-0.0.1.dist-info/WHEEL
gendotnetclass-0.0.1.dist-info/top_level.txt
gendotnetclass-0.0.1.dist-info/RECORD
